{"_type":"export","__export_format":4,"__export_date":"2023-06-15T04:27:04.183Z","__export_source":"insomnia.desktop.app:v2021.5.3","resources":[{"_id":"req_78924e5d35a54ab38d6141ca3a7d05eb","parentId":"fld_3caa3e00ed804842a6f1e3d69b066b5e","modified":1686698253110,"created":1686623630196,"url":"{{ _['node:3000'] }}/auth/login","name":"Auth","description":"","method":"POST","body":{"mimeType":"application/json","text":"{\n\t\"email\": \"mforkan0@mysql.com\",\n\t\"password\": \"EpbTceHf\"\n}"},"parameters":[],"headers":[{"name":"Content-Type","value":"application/json","id":"pair_b43f066693174c89bc05fc9e2e10d53f"}],"authentication":{},"metaSortKey":-1679087679672,"isPrivate":false,"settingStoreCookies":true,"settingSendCookies":true,"settingDisableRenderRequestBody":false,"settingEncodeUrl":true,"settingRebuildPath":true,"settingFollowRedirects":"global","_type":"request"},{"_id":"fld_3caa3e00ed804842a6f1e3d69b066b5e","parentId":"wrk_8700274954684e079165381982412b2d","modified":1686623682322,"created":1686623630098,"name":"LGPD","description":"","environment":{},"environmentPropertyOrder":null,"metaSortKey":225,"_type":"request_group"},{"_id":"wrk_8700274954684e079165381982412b2d","parentId":null,"modified":1647894984183,"created":1646311226778,"name":"FATEC","description":"","scope":"collection","_type":"workspace"},{"_id":"req_5a119674c5d6478bb5d8f9976abbd08f","parentId":"fld_3caa3e00ed804842a6f1e3d69b066b5e","modified":1686623846390,"created":1686623709826,"url":"{{ _['node:3000'] }}/mail/send-email","name":"Send Email","description":"","method":"POST","body":{"mimeType":"application/json","text":"{\n\t\"email\": \"gabriel.cleite@outlook.com\",\n\t\"message\": \"man, deixa quieto\"\n}"},"parameters":[],"headers":[{"name":"Content-Type","value":"application/json","id":"pair_b43f066693174c89bc05fc9e2e10d53f"}],"authentication":{},"metaSortKey":-1679087679665.75,"isPrivate":false,"settingStoreCookies":true,"settingSendCookies":true,"settingDisableRenderRequestBody":false,"settingEncodeUrl":true,"settingRebuildPath":true,"settingFollowRedirects":"global","_type":"request"},{"_id":"req_85602dbc5fa24daf8995554ea4201e99","parentId":"fld_056ccb847d3048b68e320a95d3151c15","modified":1686698287375,"created":1686623630108,"url":"{{ _['node:3000'] }}/users","name":"index","description":"","method":"GET","body":{},"parameters":[],"headers":[],"authentication":{"type":"bearer","token":"{{ _.jwt }}"},"metaSortKey":-1677874808659,"isPrivate":false,"settingStoreCookies":true,"settingSendCookies":true,"settingDisableRenderRequestBody":false,"settingEncodeUrl":true,"settingRebuildPath":true,"settingFollowRedirects":"global","_type":"request"},{"_id":"fld_056ccb847d3048b68e320a95d3151c15","parentId":"fld_3caa3e00ed804842a6f1e3d69b066b5e","modified":1686623630103,"created":1686623630103,"name":"Users","description":"","environment":{},"environmentPropertyOrder":null,"metaSortKey":-1679087679647,"_type":"request_group"},{"_id":"req_ff73d043ef53447ebf196c4f3eeffc44","parentId":"fld_056ccb847d3048b68e320a95d3151c15","modified":1686698596543,"created":1686623630121,"url":"{{ _['node:3000'] }}/users/eff8e91d-f219-42cc-9902-a4fa5aebd5441","name":"show","description":"","method":"GET","body":{},"parameters":[],"headers":[],"authentication":{"type":"bearer","token":"{{ _.jwt }}"},"metaSortKey":-1677874808634,"isPrivate":false,"settingStoreCookies":true,"settingSendCookies":true,"settingDisableRenderRequestBody":false,"settingEncodeUrl":true,"settingRebuildPath":true,"settingFollowRedirects":"global","_type":"request"},{"_id":"req_188a2660c021444b98e0cf290c9419f1","parentId":"fld_056ccb847d3048b68e320a95d3151c15","modified":1686698417815,"created":1686623630113,"url":"{{ _['node:3000'] }}/users","name":"Create","description":"","method":"POST","body":{"mimeType":"application/json","text":"{\n\t\"name\": \"Gabs\",\n  \"email\": \"gabs@gmail.com\",\n  \"password\": \"1234\",\n  \"cpf\": \"46284318847\",\n  \"phoneNumber\": \"12981149277\"\n}"},"parameters":[],"headers":[{"name":"Content-Type","value":"application/json","id":"pair_0a708deba0f541db94cddad1a1e3718b"}],"authentication":{},"metaSortKey":-1677874808609,"isPrivate":false,"settingStoreCookies":true,"settingSendCookies":true,"settingDisableRenderRequestBody":false,"settingEncodeUrl":true,"settingRebuildPath":true,"settingFollowRedirects":"global","_type":"request"},{"_id":"req_d91e0f39f5e44a6eb5d36f9a6995da84","parentId":"fld_056ccb847d3048b68e320a95d3151c15","modified":1686698502641,"created":1686623630123,"url":"{{ _['node:3000'] }}/users/987677ce-4774-4cdd-88ce-187b80eade8c","name":"Update","description":"","method":"PUT","body":{"mimeType":"application/json","text":"{\n\t\"name\": \"Gabs\",\n  \"email\": \"gabriel@gmail.com\",\n  \"password\": \"1234\",\n  \"cpf\": \"46284318847\",\n  \"phoneNumber\": \"12981149277\"\n}"},"parameters":[],"headers":[{"name":"Content-Type","value":"application/json","id":"pair_0a708deba0f541db94cddad1a1e3718b"}],"authentication":{"type":"bearer","token":"{{ _.jwt }}"},"metaSortKey":-1677874808584,"isPrivate":false,"settingStoreCookies":true,"settingSendCookies":true,"settingDisableRenderRequestBody":false,"settingEncodeUrl":true,"settingRebuildPath":true,"settingFollowRedirects":"global","_type":"request"},{"_id":"req_b20ef79cdabc4696934899160c729c6d","parentId":"fld_056ccb847d3048b68e320a95d3151c15","modified":1686623630117,"created":1686623630117,"url":"{{ _['node:3000'] }}/users/65171e26-fae5-4e2a-bd57-902da12080e0","name":"Delete","description":"","method":"DELETE","body":{},"parameters":[],"headers":[],"authentication":{"type":"bearer","token":"{{ _.jwt }}"},"metaSortKey":-1677874808559,"isPrivate":false,"settingStoreCookies":true,"settingSendCookies":true,"settingDisableRenderRequestBody":false,"settingEncodeUrl":true,"settingRebuildPath":true,"settingFollowRedirects":"global","_type":"request"},{"_id":"req_159cd46ad8134979a575f22a738f46c6","parentId":"fld_3a89bbf6754b4ed0890dbe74dc6da155","modified":1686783081262,"created":1686783081262,"url":"{{ _['node:3000'] }}/users","name":"index","description":"","method":"GET","body":{},"parameters":[],"headers":[],"authentication":{"type":"bearer","token":"{{ _.jwt }}"},"metaSortKey":-1677874808659,"isPrivate":false,"settingStoreCookies":true,"settingSendCookies":true,"settingDisableRenderRequestBody":false,"settingEncodeUrl":true,"settingRebuildPath":true,"settingFollowRedirects":"global","_type":"request"},{"_id":"fld_3a89bbf6754b4ed0890dbe74dc6da155","parentId":"fld_3caa3e00ed804842a6f1e3d69b066b5e","modified":1686786391727,"created":1686783081257,"name":"Products","description":"","environment":{},"environmentPropertyOrder":null,"metaSortKey":-1679067090630,"_type":"request_group"},{"_id":"req_fd26a97e252249b9a3286c4e529450ec","parentId":"fld_3a89bbf6754b4ed0890dbe74dc6da155","modified":1686783081270,"created":1686783081270,"url":"{{ _['node:3000'] }}/users/eff8e91d-f219-42cc-9902-a4fa5aebd5441","name":"show","description":"","method":"GET","body":{},"parameters":[],"headers":[],"authentication":{"type":"bearer","token":"{{ _.jwt }}"},"metaSortKey":-1677874808634,"isPrivate":false,"settingStoreCookies":true,"settingSendCookies":true,"settingDisableRenderRequestBody":false,"settingEncodeUrl":true,"settingRebuildPath":true,"settingFollowRedirects":"global","_type":"request"},{"_id":"req_7374b508440b458d9dbe2ab4687c49c3","parentId":"fld_3a89bbf6754b4ed0890dbe74dc6da155","modified":1686783081267,"created":1686783081267,"url":"{{ _['node:3000'] }}/users","name":"Create","description":"","method":"POST","body":{"mimeType":"application/json","text":"{\n\t\"name\": \"Gabs\",\n  \"email\": \"gabs@gmail.com\",\n  \"password\": \"1234\",\n  \"cpf\": \"46284318847\",\n  \"phoneNumber\": \"12981149277\"\n}"},"parameters":[],"headers":[{"name":"Content-Type","value":"application/json","id":"pair_0a708deba0f541db94cddad1a1e3718b"}],"authentication":{},"metaSortKey":-1677874808609,"isPrivate":false,"settingStoreCookies":true,"settingSendCookies":true,"settingDisableRenderRequestBody":false,"settingEncodeUrl":true,"settingRebuildPath":true,"settingFollowRedirects":"global","_type":"request"},{"_id":"req_54e7200aed4643048936046601aa33bc","parentId":"fld_3a89bbf6754b4ed0890dbe74dc6da155","modified":1686783081271,"created":1686783081271,"url":"{{ _['node:3000'] }}/users/987677ce-4774-4cdd-88ce-187b80eade8c","name":"Update","description":"","method":"PUT","body":{"mimeType":"application/json","text":"{\n\t\"name\": \"Gabs\",\n  \"email\": \"gabriel@gmail.com\",\n  \"password\": \"1234\",\n  \"cpf\": \"46284318847\",\n  \"phoneNumber\": \"12981149277\"\n}"},"parameters":[],"headers":[{"name":"Content-Type","value":"application/json","id":"pair_0a708deba0f541db94cddad1a1e3718b"}],"authentication":{"type":"bearer","token":"{{ _.jwt }}"},"metaSortKey":-1677874808584,"isPrivate":false,"settingStoreCookies":true,"settingSendCookies":true,"settingDisableRenderRequestBody":false,"settingEncodeUrl":true,"settingRebuildPath":true,"settingFollowRedirects":"global","_type":"request"},{"_id":"req_48351919beeb4d80945f995c0649ae55","parentId":"fld_3a89bbf6754b4ed0890dbe74dc6da155","modified":1686783081268,"created":1686783081268,"url":"{{ _['node:3000'] }}/users/65171e26-fae5-4e2a-bd57-902da12080e0","name":"Delete","description":"","method":"DELETE","body":{},"parameters":[],"headers":[],"authentication":{"type":"bearer","token":"{{ _.jwt }}"},"metaSortKey":-1677874808559,"isPrivate":false,"settingStoreCookies":true,"settingSendCookies":true,"settingDisableRenderRequestBody":false,"settingEncodeUrl":true,"settingRebuildPath":true,"settingFollowRedirects":"global","_type":"request"},{"_id":"req_4d1da74ed33146a789b5ae19f9c467fc","parentId":"fld_99854e003c264f5f887e3de413282cfa","modified":1686783075133,"created":1686783075133,"url":"{{ _['node:3000'] }}/users","name":"index","description":"","method":"GET","body":{},"parameters":[],"headers":[],"authentication":{"type":"bearer","token":"{{ _.jwt }}"},"metaSortKey":-1677874808659,"isPrivate":false,"settingStoreCookies":true,"settingSendCookies":true,"settingDisableRenderRequestBody":false,"settingEncodeUrl":true,"settingRebuildPath":true,"settingFollowRedirects":"global","_type":"request"},{"_id":"fld_99854e003c264f5f887e3de413282cfa","parentId":"fld_3caa3e00ed804842a6f1e3d69b066b5e","modified":1686783075131,"created":1686783075131,"name":"Purchase","description":"","environment":{},"environmentPropertyOrder":null,"metaSortKey":-1679046501613,"_type":"request_group"},{"_id":"req_47dc10ade66d4ba1ae4fc1f1cdace0a0","parentId":"fld_99854e003c264f5f887e3de413282cfa","modified":1686783075139,"created":1686783075139,"url":"{{ _['node:3000'] }}/users/eff8e91d-f219-42cc-9902-a4fa5aebd5441","name":"show","description":"","method":"GET","body":{},"parameters":[],"headers":[],"authentication":{"type":"bearer","token":"{{ _.jwt }}"},"metaSortKey":-1677874808634,"isPrivate":false,"settingStoreCookies":true,"settingSendCookies":true,"settingDisableRenderRequestBody":false,"settingEncodeUrl":true,"settingRebuildPath":true,"settingFollowRedirects":"global","_type":"request"},{"_id":"req_f1f4db0d277f4359a15280fe1fec5da3","parentId":"fld_99854e003c264f5f887e3de413282cfa","modified":1686783075134,"created":1686783075134,"url":"{{ _['node:3000'] }}/users","name":"Create","description":"","method":"POST","body":{"mimeType":"application/json","text":"{\n\t\"name\": \"Gabs\",\n  \"email\": \"gabs@gmail.com\",\n  \"password\": \"1234\",\n  \"cpf\": \"46284318847\",\n  \"phoneNumber\": \"12981149277\"\n}"},"parameters":[],"headers":[{"name":"Content-Type","value":"application/json","id":"pair_0a708deba0f541db94cddad1a1e3718b"}],"authentication":{},"metaSortKey":-1677874808609,"isPrivate":false,"settingStoreCookies":true,"settingSendCookies":true,"settingDisableRenderRequestBody":false,"settingEncodeUrl":true,"settingRebuildPath":true,"settingFollowRedirects":"global","_type":"request"},{"_id":"req_1b1e23d48320407db3e759caebdcd555","parentId":"fld_99854e003c264f5f887e3de413282cfa","modified":1686783075141,"created":1686783075141,"url":"{{ _['node:3000'] }}/users/987677ce-4774-4cdd-88ce-187b80eade8c","name":"Update","description":"","method":"PUT","body":{"mimeType":"application/json","text":"{\n\t\"name\": \"Gabs\",\n  \"email\": \"gabriel@gmail.com\",\n  \"password\": \"1234\",\n  \"cpf\": \"46284318847\",\n  \"phoneNumber\": \"12981149277\"\n}"},"parameters":[],"headers":[{"name":"Content-Type","value":"application/json","id":"pair_0a708deba0f541db94cddad1a1e3718b"}],"authentication":{"type":"bearer","token":"{{ _.jwt }}"},"metaSortKey":-1677874808584,"isPrivate":false,"settingStoreCookies":true,"settingSendCookies":true,"settingDisableRenderRequestBody":false,"settingEncodeUrl":true,"settingRebuildPath":true,"settingFollowRedirects":"global","_type":"request"},{"_id":"req_89884bd5e7c5440dae1603ecb761b378","parentId":"fld_99854e003c264f5f887e3de413282cfa","modified":1686783075136,"created":1686783075136,"url":"{{ _['node:3000'] }}/users/65171e26-fae5-4e2a-bd57-902da12080e0","name":"Delete","description":"","method":"DELETE","body":{},"parameters":[],"headers":[],"authentication":{"type":"bearer","token":"{{ _.jwt }}"},"metaSortKey":-1677874808559,"isPrivate":false,"settingStoreCookies":true,"settingSendCookies":true,"settingDisableRenderRequestBody":false,"settingEncodeUrl":true,"settingRebuildPath":true,"settingFollowRedirects":"global","_type":"request"},{"_id":"env_3de03d386c63ca1817df171e7cb4b9896d667f07","parentId":"wrk_8700274954684e079165381982412b2d","modified":1686698336495,"created":1646311226793,"name":"Base Environment","data":{"node:3000":"http://localhost:3000","mogenius":"https://owl-partners-b-prod-fatec-vg4k4y.mo4.mogenius.io","owl_render":"https://owlpartners.onrender.com","jwt":"eyJhbGciOiJIUzI1NiIsInR5cCI6IkpXVCJ9.eyJzdWIiOiI4YTBhMjg4Ny01M2UyLTQ4NjUtOTJiZi0zMmEyY2M2YWRmZTUiLCJlbWFpbCI6Im1mb3JrYW4wQG15c3FsLmNvbSIsImlhdCI6MTY4NjY5ODI1NCwiZXhwIjoxNjg2Nzg0NjU0fQ.z8LC3NUrJSzWIwR3h92l21dHepzxcKJ0z6NOZnh0SWc","jwt2":"eyJhbGciOiJIUzI1NiIsInR5cCI6IkpXVCJ9.eyJzdWIiOiI4YTBhMjg4Ny01M2UyLTQ4NjUtOTJiZi0zMmEyY2M2YWRmZTUiLCJlbWFpbCI6Im1mb3JrYW4wQG15c3FsLmNvbSIsImlhdCI6MTY4NjY5ODI1NCwiZXhwIjoxNjg2Nzg0NjU0fQ.z8LC3NUrJSzWIwR3h92l21dHepzxcKJ0z6NOZnh0SWc"},"dataPropertyOrder":{"&":["node:3000","mogenius","owl_render","jwt","jwt2"]},"color":null,"isPrivate":false,"metaSortKey":1646311226793,"_type":"environment"},{"_id":"jar_3de03d386c63ca1817df171e7cb4b9896d667f07","parentId":"wrk_8700274954684e079165381982412b2d","modified":1685918354121,"created":1646311226796,"name":"Default Jar","cookies":[{"key":"JSESSIONID","value":"1B680BF40B3E0B75DADC18F6D491FE2D","domain":"localhost","path":"/","httpOnly":true,"hostOnly":true,"creation":"2022-03-25T22:03:07.868Z","lastAccessed":"2022-06-14T00:12:50.598Z","id":"07956935801768794"},{"key":"mongo-express","value":"s%3ALWnvbIlbOwZrSbURqshsIzurXmpKBjIw.z9MsLEj5f6CaIt9EHrH7LQi%2BVeK3VSFSJbcdK%2FCe8Hg","domain":"localhost","path":"/","httpOnly":true,"hostOnly":true,"creation":"2022-03-28T19:40:26.504Z","lastAccessed":"2022-03-28T19:40:26.504Z","id":"8083143092549281"},{"key":"__cf_bm","value":"dZTWykph3484le_an2zSkxpjCeEbe.0VUvkGfI2CMQ4-1685918354-0-AezDQgt3evBiso4rr7pRdipuv1UEomv5X5q6QITayIOpVXekBskm98XHyZYFUrG086IHba9Hu8kTPP8+WwXwFqo=","expires":"2023-06-04T23:09:14.000Z","domain":"onrender.com","path":"/","secure":true,"httpOnly":true,"extensions":["SameSite=None"],"hostOnly":false,"creation":"2023-05-10T12:07:02.786Z","lastAccessed":"2023-06-04T22:39:14.116Z","id":"13808703139285017"},{"key":"_cfuvid","value":"P3ceLo3SJSoz1iaUwCf.ldjNlaDW5jHzYUZIJBdgEJA-1685794448762-0-604800000","domain":"onrender.com","path":"/","secure":true,"httpOnly":true,"extensions":["SameSite=None"],"hostOnly":false,"creation":"2023-05-10T12:07:02.788Z","lastAccessed":"2023-06-03T12:14:08.790Z","id":"8137014200816466"}],"_type":"cookie_jar"},{"_id":"spc_5486d8be6f244540a8df910ce87fd56b","parentId":"wrk_8700274954684e079165381982412b2d","modified":1646311226782,"created":1646311226782,"fileName":"Autobots","contents":"","contentType":"yaml","_type":"api_spec"}]}